{"name":"Kronface","tagline":"An Opensource UI framework built for cron to exemplify the experiance of scheduling jobs","body":"### Welcome to KronFace\r\nAn intuitive open-source user interface (UI) built for cron to exemplify the experience of scheduling jobs in Linux, Windows and Mac environment. It can be useful for administrators and developers as an add on for conveniently scheduling jobs and keeping tracks of it.\r\n\r\n### Intuitive UI\r\nNew aesthetics of scheduling jobs for a globally integrated environment.\r\n\r\n### Opensource\r\nFor the community, By the community. Totally free and open to suggestions, customization's and upgrades.\r\n\r\n### Experience\r\nChanges how people schedule jobs using Cron from unix like scripting to easy, effective, globally accessible web application.\r\n\r\n### Cron\r\nIt runs on top of Crontab (an opensource unix-like job scheduler), so Cron should be installed on the server to schedule jobs. For more information on Cron setup and Crontab utility please refer to http://crontab.org/\r\n\r\n### Apache Tomcat\r\nThe app can be deployed using a web contained like Apache Tomcat, which is lightweight and easy to handle. For more information on Apache Tomcat setup and deployments please refer to http://tomcat.apache.org/\r\n\r\n### Convenient\r\nJust provide details for when you want the job to run and a link to the run-able file and its done. The app will auto schedule the jobs for you without.\r\n\r\n### Author\r\n@shagun008 &copy; Shagun Bhardwaj 2013.\r\n\r\n### Support or Contact\r\nHaving trouble with KronFace? Email me at shagun008@gmail.com and I’ll help you sort it out.","google":"","note":"Don't delete this file! It's used internally to help with page regeneration."}